pytest_git_selector/cmd.py
pytest_git_selector/errors.py
pytest_git_selector/plugin.py
pytest_git_selector/selector.py
pytest_git_selector/util.py
pytest_git_selector-0.0.1.dist-info/METADATA
pytest_git_selector-0.0.1.dist-info/WHEEL
pytest_git_selector-0.0.1.dist-info/entry_points.txt
pytest_git_selector-0.0.1.dist-info/top_level.txt
pytest_git_selector-0.0.1.dist-info/RECORD
