Metadata-Version: 2.1
Name: pytest-git-selector
Version: 0.0.1
Summary: Utility to select tests that have had its dependencies modified (as identified by git diff)
Home-page: https://github.com/05798/pytest-git-selector
Author: Leo Lark
License: MIT
Project-URL: Homepage, https://github.com/05798/pytest-git-selector
Project-URL: Source, https://github.com/05798/pytest-git-selector
Project-URL: Bug Tracker, https://github.com/05798/pytest-git-selector/issues
Keywords: pytest,git
Classifier: Programming Language :: Python :: 3
Classifier: Framework :: Pytest
Requires-Python: >=3.8
Requires-Dist: gitpython
Requires-Dist: importlab
Requires-Dist: networkx
